MANIFEST.in
README.rst
setup.cfg
setup.py
docs/HISTORY.rst
ocqm_cohort_website/.DS_Store
ocqm_cohort_website/__init__.py
ocqm_cohort_website/builder.py
ocqm_cohort_website/content.py
ocqm_cohort_website/db.py
ocqm_cohort_website/locale.py
ocqm_cohort_website/paths.py
ocqm_cohort_website/scripts.py
ocqm_cohort_website/server.py
ocqm_cohort_website.egg-info/PKG-INFO
ocqm_cohort_website.egg-info/SOURCES.txt
ocqm_cohort_website.egg-info/dependency_links.txt
ocqm_cohort_website.egg-info/entry_points.txt
ocqm_cohort_website.egg-info/not-zip-safe
ocqm_cohort_website.egg-info/requires.txt
ocqm_cohort_website.egg-info/top_level.txt
ocqm_cohort_website/example/.DS_Store
ocqm_cohort_website/example/cohort.yml
ocqm_cohort_website/example/media/images/about_us.jpg
ocqm_cohort_website/example/media/images/businessman.jpg
ocqm_cohort_website/example/media/images/chart.png
ocqm_cohort_website/example/media/images/hipster.jpg
ocqm_cohort_website/example/media/images/hospital_logo.png
ocqm_cohort_website/example/media/images/index.jpg
ocqm_cohort_website/example/media/images/no-image.jpg
ocqm_cohort_website/example/media/images/patients.jpg
ocqm_cohort_website/example/media/images/research.jpg
ocqm_cohort_website/example/media/images/sponsoring.jpg
ocqm_cohort_website/example/media/images/woman.jpg
ocqm_cohort_website/example/pages/about_us.en.md
ocqm_cohort_website/example/pages/index.en.md
ocqm_cohort_website/example/pages/research.en.md
ocqm_cohort_website/locale/ocqm_cohort_website.pot
ocqm_cohort_website/locale/de/LC_MESSAGES/messages.mo
ocqm_cohort_website/locale/de/LC_MESSAGES/messages.po
ocqm_cohort_website/locale/fr/LC_MESSAGES/messages.mo
ocqm_cohort_website/locale/fr/LC_MESSAGES/messages.po
ocqm_cohort_website/tests/__init__.py
ocqm_cohort_website/tests/conftest.py
ocqm_cohort_website/tests/test_builder.py
ocqm_cohort_website/tests/test_db.py
ocqm_cohort_website/tests/test_locale.py
ocqm_cohort_website/tests/test_paths.py
ocqm_cohort_website/tests/test_server.py
ocqm_cohort_website/theme/_base.html
ocqm_cohort_website/theme/index.html
ocqm_cohort_website/theme/media/fonts/FontAwesome.otf
ocqm_cohort_website/theme/media/fonts/fontawesome-webfont.eot
ocqm_cohort_website/theme/media/fonts/fontawesome-webfont.svg
