Metadata-Version: 1.1
Name: ocqm-cohort-website
Version: 0.1.9
Summary: A tool to build a static website for OCQM cohorts.
Home-page: https://github.com/seantis/ocqm_cohort_website
Author: Seantis GmbH
Author-email: info@seantis.ch
License: MIT
Platform: any
Classifier: Development Status :: 4 - Beta
Classifier: Intended Audience :: Developers
Classifier: License :: OSI Approved :: MIT License
Classifier: Operating System :: OS Independent
Classifier: Programming Language :: Python
Classifier: Programming Language :: Python :: 3
Classifier: Topic :: Software Development :: Libraries :: Python Modules
